docrepr/__init__.py
docrepr/conf.py
docrepr/sphinxify.py
docrepr/utils.py
docrepr/js/bootstrap.js
docrepr/js/collapse_sections.js
docrepr/js/copy_button.js
docrepr/js/fix_image_paths.js
docrepr/js/jquery.js
docrepr/js/math_config.js
docrepr/js/move_outline.js
docrepr/js/utils.js
docrepr/sphinxext/__init__.py
docrepr/static/css/bootstrap.css
docrepr/static/css/default.css
docrepr/static/css/pygments.css
docrepr/static/images/collapse_expand.png
docrepr/templates/layout.html
docrepr/templates/rich_repr.html
docrepr/templates/warning.html
docrepr/tests/__init__.py
docrepr/tests/test_output.py
docrepr-0.2.0.dist-info/AUTHORS.md
docrepr-0.2.0.dist-info/LICENSE.txt
docrepr-0.2.0.dist-info/METADATA
docrepr-0.2.0.dist-info/WHEEL
docrepr-0.2.0.dist-info/top_level.txt
docrepr-0.2.0.dist-info/RECORD
