Metadata-Version: 2.1
Name: docrepr
Version: 0.2.0
Summary: Renders Python docstrings to rich HTML
Home-page: https://github.com/spyder-ide/docrepr
Author: Tim Dumol and the Spyder Development Team
Author-email: spyder.python@gmail.com
Maintainer: Spyder Development Team and Docrepr Contributors
Maintainer-email: spyder.python@gmail.com
License: BSD-3-clause
Project-URL: Github, https://github.com/spyder-ide/docrepr
Project-URL: Bug Tracker, https://github.com/spyder-ide/docrepr/issues
Project-URL: Parent Project, https://www.spyder-ide.org/
Keywords: Sphinx docstrings renderer HTML Spyder IPython help formatter
Platform: UNKNOWN
Classifier: Development Status :: 4 - Beta
Classifier: Environment :: Web Environment
Classifier: Framework :: IPython
Classifier: Framework :: Jupyter
Classifier: Framework :: Matplotlib
Classifier: Framework :: Sphinx
Classifier: Intended Audience :: Developers
Classifier: Intended Audience :: Science/Research
Classifier: License :: OSI Approved :: BSD License
Classifier: Operating System :: OS Independent
Classifier: Programming Language :: Python :: 3
Classifier: Programming Language :: Python :: 3 :: Only
Classifier: Programming Language :: Python :: 3.6
Classifier: Programming Language :: Python :: 3.7
Classifier: Programming Language :: Python :: 3.8
Classifier: Programming Language :: Python :: 3.9
Classifier: Programming Language :: Python :: 3.10
Classifier: Topic :: Documentation :: Sphinx
Classifier: Topic :: Scientific/Engineering :: Visualization
Classifier: Topic :: Software Development :: Documentation
Classifier: Topic :: Software Development :: Libraries :: Python Modules
Classifier: Topic :: Text Processing :: Markup :: reStructuredText
Classifier: Topic :: Utilities
Requires-Python: >=3.6
Provides-Extra: plot
Provides-Extra: test
Provides-Extra: visual_test
License-File: AUTHORS.md
License-File: LICENSE.txt
